[
	{
		"name": "Majorelle Blue",
		"author": "Jesus Ruiz",
		"url": "https://drive.google.com/uc?id=1o5pvZwZs5LgFxn3Pd6SXtrgqgZ0ktkPR",
		"downloadable": true,
		"copyright": "CreativeCommons Attribution-ShareALike"
	},{
		"name": "iOS Red Dark",
		"author": "Apple",
		"url": "https://drive.google.com/uc?id=1f3X87EHhp-IyTzkpuw95V3glKmb0l1N2",
		"downloadable": true,
		"copyright": "CreativeCommons Attribution-ShareALike"
	},{
		"name": "Fractal Art 1",
		"author": "Jesus Ruiz",
		"url": "https://drive.google.com/uc?id=1mi8eLCnsBdeppfhYRGywteEUd674dU0W",
		"downloadable": true,
		"copyright": "CreativeCommons Attribution-ShareALike"
	},{
		"name": "Fractal Art 2",
		"author": "Jesus Ruiz",
		"url": "https://drive.google.com/uc?id=1VIXgNI6kUvgpTxetYW5WLFXetEVUqNjl",
		"downloadable": true,
		"copyright": "CreativeCommons Attribution-ShareALike"
	},{
		"name": "Fractal Art 3",
		"author": "YoG",
		"url": "https://drive.google.com/uc?id=1p-m_K5IsxOx_zNAleTncEKm3RSwkuaS9",
		"downloadable": true,
		"copyright": "CreativeCommons Attribution-ShareALike"
	},{
		"name": "Dark Planet",
		"author": "Daniel Olah Unsplash",
		"url": "https://drive.google.com/uc?id=1L2UuZ7pMsBipgsEqy70UPKl7kVxjWJS-",
		"downloadable": true,
		"copyright": "CreativeCommons Attribution-ShareALike"
	},{
		"name": "Biarritz, France",
		"author": "Thibault penin Unsplash",
		"url": "https://drive.google.com/uc?id=1laqYz6azoD5BGN_q1bbiHFOzSnFT8vtd",
		"downloadable": true,
		"copyright": "CreativeCommons Attribution-ShareALike"
	},{
		"name": "Pacific Beach",
		"author": "Jason leem Unsplash",
		"url": "https://drive.google.com/uc?id=1ABqlJ_IcTjYLcIFaR7vjvxkzWHwIDCgh",
		"downloadable": true,
		"copyright": "CreativeCommons Attribution-ShareALike"
	},{
		"name": "White Cibbu shelf",
		"author": "Baby QB Unsplash",
		"url": "https://drive.google.com/uc?id=1Y3JCXtFEndx5gM7cFwUqs-zHOV-m_158",
		"downloadable": true,
		"copyright": "CreativeCommons Attribution-ShareALike"
	},{
		"name": "Wooden Fence Close Up",
		"author": "Carolina PImenta Unsplash",
		"url": "https://drive.google.com/uc?id=1Qxb3V-jz51n7ym8V9XOrI6Wud_ClqkIj",
		"downloadable": true,
		"copyright": "CreativeCommons Attribution-ShareALike"
	},{
		"name": "Sea waves",
		"author": "Unknown",
		"url": "https://drive.google.com/uc?id=1x44qM9lzKSO8w-SxxzXh3OupW74nsleU",
		"downloadable": true,
		"copyright": "CreativeCommons Attribution-ShareALike"
	},{
		"name": "Sand",
		"author": "adrien Olichon",
		"url": "https://drive.google.com/uc?id=161AKJ1ZyORBAkyzswGGYhZZUUyWYCfRu",
		"downloadable": true,
		"copyright": "CreativeCommons Attribution-ShareALike"
	},{
		"name": "Graphiti",
		"author": "JFL Unsplash",
		"url": "https://drive.google.com/uc?id=1BLWI5Y9sO2odhbbRE6BGJdFiWmtPPyNw",
		"downloadable": true,
		"copyright": "CreativeCommons Attribution-ShareALike"
	},{
		"name": "Electro Parade from Montreal,",
		"author": "Camille Couvez Unsplash",
		"url": "https://drive.google.com/uc?id=1vXCh6Y5vW0VOuU4bry3W2C-mUT0ygU2p",
		"downloadable": true,
		"copyright": "CreativeCommons Attribution-ShareALike"
	},{ 
		"name": "hulhule Island",
		"author": "Saffu Unsplash",
		"url": "https://drive.google.com/uc?id=1vtCW2rlg2rIO_s7qIeEiMK5nKNWrWNRs",
		"downloadable": true,
		"copyright": "CreativeCommons Attribution-ShareALike"
	},{
		"name": "Sea Wave",
		"author": "YoG",
		"url": "https://drive.google.com/uc?id=1XCCLRXhBDAOI17DWaFjLrkWz-r5ZSzqB",
		"downloadable": true,
		"copyright": "CreativeCommons Attribution-ShareALike"
	},{
		"name": "Drops on Leafs",
		"author": "YoG",
		"url": "https://drive.google.com/uc?id=1VV7JXeN57ANl1Vs6U1Vp9TTa-1SrZKhW",
		"downloadable": true,
		"copyright": "CreativeCommons Attribution-ShareALike"
	},{
		"name": "Red Mable leaves",
		"author": "Annie Spratt Unsplash",
		"url": "https://drive.google.com/uc?id=107EghbiCu02F5j0zZ9y2rQZ09x7mxX_P",
		"downloadable": true,
		"copyright": "CreativeCommons Attribution-ShareALike"
	},{
		"name": "Abstract Wall",
		"author": "Daniel Olah Unsplash",
		"url": "https://drive.google.com/uc?id=1Gwi5ZJvrHSN2-sNqbwXUeH17zngUPaLW",
		"downloadable": true,
		"copyright": "CreativeCommons Attribution-ShareALike"
	},{
		"name": "Green linear leaf",
		"author": "Mona Eendra Unsplash",
		"url": "https://drive.google.com/uc?id=1bIS_6Xu6Zh08woPTArV3yA0rxZtDAPbI",
		"downloadable": true,
		"copyright": "CreativeCommons Attribution-ShareALike"
	},{
		"name": "Abstract Painting photo",
		"author": "Jon Tyson Unsplash",
		"url": "https://drive.google.com/uc?id=1Rlr_CRhfnf8jA4-WeDdemrN2Ax3jjW2o",
		"downloadable": true,
		"copyright": "CreativeCommons Attribution-ShareALike"
	},{
		"name": "Simple material wallpaper",
		"author": "YoG",
		"url": "https://drive.google.com/uc?id=16GC_qQPiUTOCK9i1aAp4rLB3K9xPtNIA/",
		"downloadable": true,
		"copyright": "CreativeCommons Attribution-ShareALike"
	},{
		"name": "Blue Blobs",
		"author": "YoG",
		"url": "https://drive.google.com/uc?id=12W5ORhf3LtWIqh8MuB1XmfF4JRoqZw8g",
		"downloadable": true,
		"copyright": "CreativeCommons Attribution-ShareALike"
	},{
		"name": "Pattern Wall",
		"author": "YoG",
		"url": "https://drive.google.com/uc?id=1-L2DpUYw0AuGrhHwnoXarK4kFbR-YpS8",
		"downloadable": true,
		"copyright": "CreativeCommons Attribution-ShareALike"
	}	
]
